scaffold/__init__.py
scaffold/scaffold.py
scaffold/kit/__init__.py
scaffold/kit/colors.py
scaffold/kit/patterns.py
scaffold/kit/templates.py
scaffold/kit/utils.py
scaffold/management/__init__.py
scaffold/management/commands/__init__.py
scaffold/management/commands/scaffold-app.py
scaffold/management/commands/scaffold.py
manny-0.1.4.dist-info/LICENSE
manny-0.1.4.dist-info/METADATA
manny-0.1.4.dist-info/WHEEL
manny-0.1.4.dist-info/top_level.txt
manny-0.1.4.dist-info/RECORD
