Metadata-Version: 2.1
Name: manny
Version: 0.1.4
Summary: Django scaffold like in Ruby on Rails
Home-page: https://github.com/q0w/manny/
Author: q0w
License: MIT
Keywords: Django scaffold
Platform: UNKNOWN
Classifier: Environment :: Web Environment
Classifier: Framework :: Django :: 3.0
Classifier: Intended Audience :: Developers
Classifier: License :: OSI Approved :: MIT License
Classifier: Operating System :: OS Independent
Classifier: Natural Language :: English
Classifier: Programming Language :: Python :: 3.6
Classifier: Programming Language :: Python :: 3.7
Classifier: Programming Language :: Python :: 3.8
Classifier: Programming Language :: Python :: 3.9
Classifier: Topic :: Internet :: WWW/HTTP
Requires-Python: >=3.6
Requires-Dist: Django (>=1.11)
Requires-Dist: black
Requires-Dist: astor
